digemail-0.1.0.dist-info/METADATA
digemail-0.1.0.dist-info/WHEEL
digemail/__init__.py
digemail/__main__.py
digemail-0.1.0.dist-info/RECORD
